scanreq/__about__.py
scanreq/__init__.py
scanreq/__main__.py
scanreq/scanner.py
scanreq-0.0.9.dist-info/METADATA
scanreq-0.0.9.dist-info/WHEEL
scanreq-0.0.9.dist-info/entry_points.txt
scanreq-0.0.9.dist-info/licenses/LICENSE
scanreq-0.0.9.dist-info/RECORD
