Metadata-Version: 2.3
Name: scanreq
Version: 0.0.9
Summary: Python tool to scan all unused packages in requirements.txt file for your project.
Project-URL: Changelog, https://github.com/agusmakmun/scan-unused-requirements/releases
Project-URL: Documentation, https://github.com/agusmakmun/scan-unused-requirements
Project-URL: Issues, https://github.com/agusmakmun/scan-unused-requirements/issues
Project-URL: Source, https://github.com/agusmakmun/scan-unused-requirements
Author-email: agusmakmun <summon.agus@gmail.com>
License-Expression: MIT
License-File: LICENSE
Keywords: packages,requirements,scan,unused
Classifier: Development Status :: 5 - Production/Stable
Classifier: Environment :: Console
Classifier: Intended Audience :: Developers
Classifier: License :: OSI Approved :: MIT License
Classifier: Operating System :: OS Independent
Classifier: Programming Language :: Python
Classifier: Programming Language :: Python :: 3 :: Only
Classifier: Programming Language :: Python :: 3.8
Classifier: Programming Language :: Python :: 3.9
Classifier: Programming Language :: Python :: 3.10
Classifier: Programming Language :: Python :: 3.11
Classifier: Programming Language :: Python :: 3.12
Requires-Python: >=3.8
Requires-Dist: importlib-metadata>=7.1.0
